bembel/__init__.py
bembel/bembel_constants.py
pybembel-0.5.5.data/scripts/bembel
pybembel-0.5.5.dist-info/LICENSE
pybembel-0.5.5.dist-info/METADATA
pybembel-0.5.5.dist-info/WHEEL
pybembel-0.5.5.dist-info/top_level.txt
pybembel-0.5.5.dist-info/RECORD
